randcw/__init__.py
randcw_Renz420-0.0.1.dist-info/LICENSE
randcw_Renz420-0.0.1.dist-info/METADATA
randcw_Renz420-0.0.1.dist-info/WHEEL
randcw_Renz420-0.0.1.dist-info/top_level.txt
randcw_Renz420-0.0.1.dist-info/RECORD
