Metadata-Version: 2.1
Name: randcw-Renz420
Version: 0.0.1
Summary: Package for uploading data to cloudwatch using python
Home-page: https://github.com/Rene-Voiro/Randtocw.git
Author: Rene
Author-email: ren@voiro.com
License: UNKNOWN
Platform: UNKNOWN
Classifier: Programming Language :: Python :: 3
Classifier: License :: OSI Approved :: MIT License
Classifier: Operating System :: OS Independent
Requires-Python: >=3.6
